prelawsql/__init__.py
prelawsql/__main__.py
prelawsql/authors.py
prelawsql/citations.py
prelawsql/clean.py
prelawsql/config.py
prelawsql/db.py
prelawsql/dumper.py
prelawsql/fts.py
prelawsql/header.py
prelawsql/listing.py
prelawsql/logger.py
prelawsql/markdown.py
prelawsql/network.py
prelawsql/sanitizer.py
prelawsql/statutes.py
prelawsql/patterns/__init__.py
prelawsql/patterns/footnote.py
prelawsql/patterns/decision/__init__.py
prelawsql/patterns/decision/casename.py
prelawsql/patterns/decision/courts.py
prelawsql/patterns/decision/cullables.py
prelawsql/patterns/decision/fallo.py
prelawsql/patterns/decision/phrase.py
prelawsql/patterns/decision/regex.py
prelawsql/patterns/statute/__init__.py
prelawsql/patterns/statute/const.py
prelawsql/patterns/statute/digits.py
prelawsql/patterns/statute/roc.py
prelawsql/patterns/statute/spain.py
prelawsql-0.0.13.dist-info/METADATA
prelawsql-0.0.13.dist-info/WHEEL
prelawsql-0.0.13.dist-info/entry_points.txt
prelawsql-0.0.13.dist-info/top_level.txt
prelawsql-0.0.13.dist-info/RECORD
