Metadata-Version: 2.4
Name: prelawsql
Version: 0.0.13
Summary: Toolkit for Philippine rules.
Requires-Python: >=3.13
Requires-Dist: citation-utils>=0.5.0
Requires-Dist: citation-title>=0.0.2
Requires-Dist: corpus-judge>=0.2.0
Requires-Dist: environs>=14.3
Requires-Dist: sqlite-utils>=3.38
Requires-Dist: rich>=14.1
Requires-Dist: html-sanitizer>=2.6.0
Requires-Dist: pyyaml>=6.0.3
Requires-Dist: beautifulsoup4>=4.14
Requires-Dist: markdown>=3.9
Requires-Dist: httpx>=0.28.1
Requires-Dist: python-frontmatter>=1.1.0
Requires-Dist: python-slugify>=8.0
